{
  "authorDailyContributionsMap": {
    "iqbxl": [
      {
        "date": "2020-09-27",
        "commitResults": [
          {
            "hash": "cf920401b6665e3feaa5cc673ec2d6bc3d8ac44c",
            "messageTitle": "Update profile picture, UG and DG",
            "messageBody": "",
            "fileTypesAndContributionMap": {
              "docs": {
                "insertions": 24,
                "deletions": 0
              }
            }
          }
        ]
      },
      {
        "date": "2020-09-28",
        "commitResults": [
          {
            "hash": "a1f92e0ed52c970af83db9b24d838f96d1ed2aed",
            "messageTitle": "Update AboutUs.md",
            "messageBody": "",
            "fileTypesAndContributionMap": {
              "docs": {
                "insertions": 5,
                "deletions": 5
              }
            }
          }
        ]
      }
    ],
    "nicholasyeo": [
      {
        "date": "2020-09-27",
        "commitResults": [
          {
            "hash": "298c0635dbfe22d673baa1b276cbea6210d1f857",
            "messageTitle": "Update UG",
            "messageBody": "",
            "fileTypesAndContributionMap": {
              "docs": {
                "insertions": 18,
                "deletions": 0
              }
            }
          },
          {
            "hash": "99257920c2f7edaf6954a95286441a482392d02c",
            "messageTitle": "Update DG",
            "messageBody": "",
            "fileTypesAndContributionMap": {
              "docs": {
                "insertions": 51,
                "deletions": 0
              }
            }
          },
          {
            "hash": "deefd14107d629ec9152030a2848b88796b22e07",
            "messageTitle": "Update user stories",
            "messageBody": "",
            "fileTypesAndContributionMap": {
              "docs": {
                "insertions": 4,
                "deletions": 2
              }
            }
          }
        ]
      },
      {
        "date": "2020-09-28",
        "commitResults": [
          {
            "hash": "3f9d2bf5b0a8f52f59b1343f06f6ef648928488d",
            "messageTitle": "Update AboutUs.md",
            "messageBody": "",
            "fileTypesAndContributionMap": {
              "docs": {
                "insertions": 5,
                "deletions": 5
              }
            }
          }
        ]
      }
    ],
    "patricktan6": [],
    "khor-jingqian": [
      {
        "date": "2020-09-21",
        "commitResults": [
          {
            "hash": "71b2aff845e633bf76066be1fc8fe1b2efc90713",
            "messageTitle": "Update README.md",
            "messageBody": "",
            "fileTypesAndContributionMap": {
              "docs": {
                "insertions": 1,
                "deletions": 1
              }
            }
          }
        ]
      },
      {
        "date": "2020-09-23",
        "commitResults": [
          {
            "hash": "dd86674b9ab1c161289bb8b51bccba64bb4dec72",
            "messageTitle": "Update UG and DG, add user picture",
            "messageBody": "",
            "fileTypesAndContributionMap": {
              "docs": {
                "insertions": 41,
                "deletions": 0
              }
            }
          },
          {
            "hash": "854575c99ca9090b7ece5239d592f606ca946b2f",
            "messageTitle": "Update DG",
            "messageBody": "",
            "fileTypesAndContributionMap": {
              "docs": {
                "insertions": 10,
                "deletions": 1
              }
            }
          }
        ]
      },
      {
        "date": "2020-09-28",
        "commitResults": [
          {
            "hash": "16ca4f359d22abdf7c2a8a151b76b30d8cb8edf2",
            "messageTitle": "Rectify config file and clean up UserGuide",
            "messageBody": "",
            "fileTypesAndContributionMap": {
              "docs": {
                "insertions": 30,
                "deletions": 130
              }
            }
          }
        ]
      }
    ],
    "Licheng-Wu": [
      {
        "date": "2020-09-16",
        "commitResults": [
          {
            "hash": "416aa5856e345ea1ad1bc569c868f422a8409d90",
            "messageTitle": "Update README.md",
            "messageBody": "",
            "fileTypesAndContributionMap": {
              "docs": {
                "insertions": 1,
                "deletions": 0
              }
            }
          }
        ]
      },
      {
        "date": "2020-09-22",
        "commitResults": [
          {
            "hash": "07e80dcac6231c9306cb53dad5fdf72ed29b5909",
            "messageTitle": "Update UserGuide.",
            "messageBody": "Added 4 functions - create new routine, delete routine, add exercise to routine and delete exercise routine descriptions to the UserGuide.\n",
            "fileTypesAndContributionMap": {
              "docs": {
                "insertions": 36,
                "deletions": 0
              }
            }
          }
        ]
      },
      {
        "date": "2020-09-23",
        "commitResults": [
          {
            "hash": "0716144b7869b86ae33abb523253e713ea0cdf7b",
            "messageTitle": "Update Developer Guide",
            "messageBody": "Added 4 use cases: Creating a new routine, deleting a routine, adding exercises to a routine, deleting exercises from a routine\n",
            "fileTypesAndContributionMap": {
              "docs": {
                "insertions": 102,
                "deletions": 0
              }
            }
          }
        ]
      },
      {
        "date": "2020-09-28",
        "commitResults": [
          {
            "hash": "492258ea7c81f13c25f2841b0fa15e489ef3f052",
            "messageTitle": "Update README.md",
            "messageBody": "",
            "fileTypesAndContributionMap": {
              "docs": {
                "insertions": 6,
                "deletions": 7
              }
            }
          },
          {
            "hash": "35e3583cb3ca0ce16976e777e4ac92c24cc1d328",
            "messageTitle": "Update AboutUs.md",
            "messageBody": "",
            "fileTypesAndContributionMap": {
              "docs": {
                "insertions": 5,
                "deletions": 5
              }
            }
          }
        ]
      }
    ]
  },
  "authorFileTypeContributionMap": {
    "iqbxl": {
      "docs": 25,
      "functional-code": 0,
      "test-code": 0
    },
    "nicholasyeo": {
      "docs": 69,
      "functional-code": 0,
      "test-code": 0
    },
    "patricktan6": {
      "docs": 0,
      "functional-code": 0,
      "test-code": 0
    },
    "khor-jingqian": {
      "docs": 72,
      "functional-code": 0,
      "test-code": 0
    },
    "Licheng-Wu": {
      "docs": 133,
      "functional-code": 0,
      "test-code": 0
    }
  },
  "authorContributionVariance": {
    "iqbxl": 14.14934,
    "nicholasyeo": 121.04207,
    "patricktan6": 0.0,
    "khor-jingqian": 593.74854,
    "Licheng-Wu": 253.4669
  },
  "authorDisplayNameMap": {
    "iqbxl": "CS2103T-T09-2 MUHA..MRAN",
    "nicholasyeo": "CS2103T-T09-2 NICH..LENG",
    "patricktan6": "CS2103T-T09-2 TAN .. ZHE",
    "khor-jingqian": "CS2103T-T09-2 KHOR..QIAN",
    "Licheng-Wu": "CS2103T-T09-2 WU L..HENG"
  }
}
