{
  "authorDailyContributionsMap": {
    "wireseo": [
      {
        "date": "2020-09-20",
        "commitResults": [
          {
            "hash": "16cb7e7942edc745c176fe77bac09fd3605b58be",
            "messageTitle": "Edit aboutus page details",
            "messageBody": "",
            "fileTypesAndContributionMap": {
              "docs": {
                "insertions": 5,
                "deletions": 5
              }
            }
          },
          {
            "hash": "0191d543516fdc92a78343b81f984e8b3b10a55e",
            "messageTitle": "Add personal portfolio markdown file",
            "messageBody": "",
            "fileTypesAndContributionMap": {
              "docs": {
                "insertions": 46,
                "deletions": 0
              }
            }
          }
        ]
      }
    ],
    "Asuraxsoul": [
      {
        "date": "2020-09-14",
        "commitResults": [
          {
            "hash": "1351c710210a116aa1f23250daac64e50e5f276e",
            "messageTitle": "Update README.md",
            "messageBody": "",
            "fileTypesAndContributionMap": {
              "docs": {
                "insertions": 1,
                "deletions": 0
              }
            }
          }
        ]
      },
      {
        "date": "2020-09-25",
        "commitResults": [
          {
            "hash": "9f45009294014579d6c5133b59769911d914c44e",
            "messageTitle": "Add Jun Jie\u0027s profile photo \u0026 Update AboutUs",
            "messageBody": "",
            "fileTypesAndContributionMap": {
              "docs": {
                "insertions": 55,
                "deletions": 29
              }
            }
          },
          {
            "hash": "714deb2cc1e3c7a7eebd578b3a9306f3e7684ae9",
            "messageTitle": "Checkstyle clean up",
            "messageBody": "",
            "fileTypesAndContributionMap": {
              "docs": {
                "insertions": 21,
                "deletions": 21
              }
            }
          }
        ]
      }
    ],
    "ngzhenteng": [
      {
        "date": "2020-09-20",
        "commitResults": [
          {
            "hash": "c3ce1a32ad8aa3b42c3451c2f99d2c90d1fee62d",
            "messageTitle": "Update UserGuide.md",
            "messageBody": "Port contents from Week 6 Draft User Guide",
            "fileTypesAndContributionMap": {
              "docs": {
                "insertions": 279,
                "deletions": 125
              }
            }
          }
        ]
      },
      {
        "date": "2020-09-23",
        "commitResults": [
          {
            "hash": "9fc42acfe288b834e8307957eb81946c7fc01bea",
            "messageTitle": "Add AboutUs and Personal Profile Page",
            "messageBody": "",
            "fileTypesAndContributionMap": {
              "docs": {
                "insertions": 61,
                "deletions": 0
              }
            }
          }
        ]
      }
    ],
    "peironggg": [
      {
        "date": "2020-09-21",
        "commitResults": [
          {
            "hash": "0cdc65874bc462c66abdaafa41cc5ec90303a335",
            "messageTitle": "Update Peirong\u0027s Aboutme",
            "messageBody": "",
            "fileTypesAndContributionMap": {
              "docs": {
                "insertions": 56,
                "deletions": 10
              }
            }
          },
          {
            "hash": "ed0aa00e3590e67a93def809ff55275b0227d373",
            "messageTitle": "Update README contents",
            "messageBody": "",
            "fileTypesAndContributionMap": {
              "docs": {
                "insertions": 6,
                "deletions": 10
              }
            }
          }
        ]
      },
      {
        "date": "2020-09-25",
        "commitResults": [
          {
            "hash": "72467328832e419cc56a732ff67d705778f45ccd",
            "messageTitle": "Update target profile and several user stories",
            "messageBody": "",
            "fileTypesAndContributionMap": {
              "docs": {
                "insertions": 10,
                "deletions": 11
              }
            }
          }
        ]
      }
    ],
    "wilinetan": [
      {
        "date": "2020-09-21",
        "commitResults": [
          {
            "hash": "f3dec379618a5e0e40d009dcb87b13ef3d04dac5",
            "messageTitle": "Update Wiline Tan\u0027s AboutUs",
            "messageBody": "",
            "fileTypesAndContributionMap": {
              "docs": {
                "insertions": 56,
                "deletions": 0
              }
            }
          },
          {
            "hash": "88258064a3067cc54182093f984deed1206b95f0",
            "messageTitle": "Update Wiline Tan\u0027s AboutUs",
            "messageBody": "",
            "fileTypesAndContributionMap": {
              "docs": {
                "insertions": 1,
                "deletions": 1
              }
            }
          }
        ]
      }
    ]
  },
  "authorFileTypeContributionMap": {
    "wireseo": {
      "docs": 47,
      "functional-code": 0,
      "test-code": 0
    },
    "Asuraxsoul": {
      "docs": 51,
      "functional-code": 0,
      "test-code": 0
    },
    "ngzhenteng": {
      "docs": 321,
      "functional-code": 0,
      "test-code": 0
    },
    "peironggg": {
      "docs": 72,
      "functional-code": 0,
      "test-code": 0
    },
    "wilinetan": {
      "docs": 50,
      "functional-code": 0,
      "test-code": 0
    }
  },
  "authorContributionVariance": {
    "wireseo": 71.23418,
    "Asuraxsoul": 360.50946,
    "ngzhenteng": 3765.3135,
    "peironggg": 160.89021,
    "wilinetan": 76.413185
  },
  "authorDisplayNameMap": {
    "wireseo": "CS2103T-W11-2 SEO ..YEON",
    "Asuraxsoul": "CS2103T-W11-2 LIM .. JIE",
    "ngzhenteng": "CS2103T-W11-2 NG Z..TENG",
    "peironggg": "CS2103T-W11-2 WU P..RONG",
    "wilinetan": "CS2103T-W11-2 WILI.. TAN"
  }
}
