{
  "authorDailyContributionsMap": {
    "Wong-ZZ": [
      {
        "date": "2020-09-10",
        "commitResults": [
          {
            "hash": "3ab24f57e13b76731434fe2e340437802eae3ba0",
            "messageTitle": "Update README.md",
            "messageBody": "",
            "fileTypesAndContributionMap": {
              "docs": {
                "insertions": 4,
                "deletions": 11
              }
            }
          }
        ]
      },
      {
        "date": "2020-09-27",
        "commitResults": [
          {
            "hash": "ca66f26d684174d8d2aaff6805518d15dd681ff2",
            "messageTitle": "Add new height field",
            "messageBody": "",
            "fileTypesAndContributionMap": {
              "functional-code": {
                "insertions": 145,
                "deletions": 22
              },
              "test-code": {
                "insertions": 237,
                "deletions": 61
              }
            }
          },
          {
            "hash": "1610d8b51306d2738ce25b8a0497649445ce5dfd",
            "messageTitle": "Fix checkstyle violations",
            "messageBody": "",
            "fileTypesAndContributionMap": {
              "functional-code": {
                "insertions": 6,
                "deletions": 1
              },
              "test-code": {
                "insertions": 1,
                "deletions": 1
              }
            }
          },
          {
            "hash": "f36d8c789b49e7b1a48b34be5f98e0e68c5d4741",
            "messageTitle": "Modify card to display unit of measurement for height",
            "messageBody": "",
            "fileTypesAndContributionMap": {
              "functional-code": {
                "insertions": 5,
                "deletions": 3
              }
            }
          },
          {
            "hash": "7b5f832a762be18bda961c6d90cb6236d9251833",
            "messageTitle": "Update AddressBookTest",
            "messageBody": "",
            "fileTypesAndContributionMap": {
              "test-code": {
                "insertions": 2,
                "deletions": 1
              }
            }
          }
        ]
      },
      {
        "date": "2020-09-28",
        "commitResults": [
          {
            "hash": "b1f1c65352f120413d5bbaeaa9fecd5177300d47",
            "messageTitle": "Fix comment typo",
            "messageBody": "",
            "fileTypesAndContributionMap": {
              "test-code": {
                "insertions": 1,
                "deletions": 1
              }
            }
          }
        ]
      }
    ],
    "wang-jun-hao": [
      {
        "date": "2020-09-22",
        "commitResults": [
          {
            "hash": "f2709316759eacaafdaa5f918dc9d8589c20df15",
            "messageTitle": "Add comments for some edit-command-tracing\u0027s methods invoked",
            "messageBody": "",
            "fileTypesAndContributionMap": {
              "functional-code": {
                "insertions": 7,
                "deletions": 0
              }
            }
          }
        ]
      },
      {
        "date": "2020-09-30",
        "commitResults": [
          {
            "hash": "6415e981830eca109fa9b2f1664b62c07e36e78a",
            "messageTitle": "Fix bug causing error in program start-up for first-time user.",
            "messageBody": "SampleDataUtil.java: add valid tag for getTagSet(), remove redundant \u0027,\u0027\n",
            "fileTypesAndContributionMap": {
              "functional-code": {
                "insertions": 1,
                "deletions": 1
              }
            }
          },
          {
            "hash": "bb263a5fd37e50240f7f9b2c878b5fb34d03acaf",
            "messageTitle": "Remove trailing whitespace in LogicManager.java",
            "messageBody": "",
            "fileTypesAndContributionMap": {
              "functional-code": {
                "insertions": 1,
                "deletions": 1
              }
            }
          },
          {
            "hash": "7721d95c6f235ea41d61251e1c9847fb4fb5de83",
            "messageTitle": "Update User Guide",
            "messageBody": "",
            "fileTypesAndContributionMap": {
              "docs": {
                "insertions": 61,
                "deletions": 104
              }
            }
          }
        ]
      }
    ],
    "divakarmal": [],
    "foojingyi": [],
    "PrestonTYR": [
      {
        "date": "2020-09-26",
        "commitResults": [
          {
            "hash": "876afbcda16e11ce25bf623590a9174b32352874",
            "messageTitle": "Add support for IC field",
            "messageBody": "",
            "fileTypesAndContributionMap": {
              "functional-code": {
                "insertions": 143,
                "deletions": 27
              },
              "test-code": {
                "insertions": 55,
                "deletions": 31
              }
            }
          },
          {
            "hash": "84f737ca4b537665c7c99f008d4550cffe5866b1",
            "messageTitle": "Fix bug in EditCommand that didn\u0027t allow user to edit Persons",
            "messageBody": "",
            "fileTypesAndContributionMap": {
              "functional-code": {
                "insertions": 6,
                "deletions": 1
              },
              "test-code": {
                "insertions": 65,
                "deletions": 42
              }
            }
          },
          {
            "hash": "b2d9ccd7f25efc16f09105067ec3ffe33d7609ac",
            "messageTitle": "Update test cases to include IC",
            "messageBody": "",
            "fileTypesAndContributionMap": {
              "test-code": {
                "insertions": 4,
                "deletions": 4
              }
            }
          }
        ]
      },
      {
        "date": "2020-09-27",
        "commitResults": [
          {
            "hash": "4ed0961e49032fb2dc7beb42f05122a7c1c253a4",
            "messageTitle": "Update AddCommand to display proper message usage string",
            "messageBody": "",
            "fileTypesAndContributionMap": {
              "functional-code": {
                "insertions": 2,
                "deletions": 5
              }
            }
          },
          {
            "hash": "966efb5b7bc82606cda20004e72aab22d2bf7d8c",
            "messageTitle": "Update tests to test for IC",
            "messageBody": "",
            "fileTypesAndContributionMap": {
              "functional-code": {
                "insertions": 7,
                "deletions": 1
              },
              "test-code": {
                "insertions": 18,
                "deletions": 5
              }
            }
          },
          {
            "hash": "e192377cf073cdc87017be58fb93e9e5f1c20a47",
            "messageTitle": "Update Ic regex and add test cases",
            "messageBody": "",
            "fileTypesAndContributionMap": {
              "functional-code": {
                "insertions": 1,
                "deletions": 1
              },
              "test-code": {
                "insertions": 66,
                "deletions": 4
              }
            }
          }
        ]
      },
      {
        "date": "2020-09-28",
        "commitResults": [
          {
            "hash": "80030cd72eca776c5ebd7e20b559d1604d358f00",
            "messageTitle": "Update code to only use IC when checking if 2 Person\u0027s are the same Person",
            "messageBody": "",
            "fileTypesAndContributionMap": {
              "functional-code": {
                "insertions": 1,
                "deletions": 3
              },
              "test-code": {
                "insertions": 10,
                "deletions": 8
              }
            }
          },
          {
            "hash": "2d0d21bbe13de2bfb5c4017d086b0a32a49d083e",
            "messageTitle": "Update test cases to check for invalid or multiple inputs of IC",
            "messageBody": "",
            "fileTypesAndContributionMap": {
              "functional-code": {
                "insertions": 5,
                "deletions": 0
              },
              "test-code": {
                "insertions": 50,
                "deletions": 8
              }
            }
          },
          {
            "hash": "e7f4fa6e8330446b4e09f4f7827199929e316c39",
            "messageTitle": "Update regex for IC so last character can only be 1 letter",
            "messageBody": "",
            "fileTypesAndContributionMap": {
              "functional-code": {
                "insertions": 1,
                "deletions": 1
              }
            }
          },
          {
            "hash": "c4f0e21373ae07058aca4430442e95fb94f1fb91",
            "messageTitle": "Update regex for IC so that first character can only be 1 letter of S, T, F or G",
            "messageBody": "",
            "fileTypesAndContributionMap": {
              "functional-code": {
                "insertions": 1,
                "deletions": 1
              },
              "test-code": {
                "insertions": 1,
                "deletions": 1
              }
            }
          },
          {
            "hash": "be2a78d7b0a2ccffeeffaeebc190cebb8c1ee03e",
            "messageTitle": "Add more test cases for invalid ICs",
            "messageBody": "",
            "fileTypesAndContributionMap": {
              "test-code": {
                "insertions": 3,
                "deletions": 1
              }
            }
          }
        ]
      },
      {
        "date": "2020-09-29",
        "commitResults": [
          {
            "hash": "83aea1c839f2497ae229cf4b2bd522d69e80ab14",
            "messageTitle": "Fix errors after resolving merge conflicts",
            "messageBody": "",
            "fileTypesAndContributionMap": {
              "functional-code": {
                "insertions": 2,
                "deletions": 4
              },
              "test-code": {
                "insertions": 7,
                "deletions": 6
              }
            }
          }
        ]
      }
    ]
  },
  "authorFileTypeContributionMap": {
    "Wong-ZZ": {
      "docs": 4,
      "functional-code": 129,
      "test-code": 167
    },
    "wang-jun-hao": {
      "docs": 61,
      "functional-code": 8,
      "test-code": 0
    },
    "divakarmal": {
      "docs": 0,
      "functional-code": 0,
      "test-code": 0
    },
    "foojingyi": {
      "docs": 0,
      "functional-code": 0,
      "test-code": 0
    },
    "PrestonTYR": {
      "docs": 0,
      "functional-code": 164,
      "test-code": 283
    }
  },
  "authorContributionVariance": {
    "Wong-ZZ": 4795.9146,
    "wang-jun-hao": 582.5972,
    "divakarmal": 0.0,
    "foojingyi": 0.0,
    "PrestonTYR": 3267.0818
  },
  "authorDisplayNameMap": {
    "Wong-ZZ": "CS2103T-F13-3 WONG.. ZHI",
    "wang-jun-hao": "CS2103T-F13-3 WANG.. HAO",
    "divakarmal": "CS2103T-F13-3 DIVA..OTRA",
    "foojingyi": "CS2103T-F13-3 FOO ..G YI",
    "PrestonTYR": "CS2103T-F13-3 PRES.. RUI"
  }
}
