{
  "authorDailyContributionsMap": {
    "Raymond0212": [],
    "danadi7": [],
    "e0316059": []
  },
  "authorFileTypeContributionMap": {
    "Raymond0212": {
      "docs": 0,
      "functional-code": 0,
      "test-code": 0
    },
    "danadi7": {
      "docs": 0,
      "functional-code": 0,
      "test-code": 0
    },
    "e0316059": {
      "docs": 0,
      "functional-code": 0,
      "test-code": 0
    }
  },
  "authorContributionVariance": {
    "Raymond0212": 0.0,
    "danadi7": 0.0,
    "e0316059": 0.0
  },
  "authorDisplayNameMap": {
    "Raymond0212": "CS2103-T16-4 CHEN..GYAN",
    "danadi7": "CS2103-T16-4 DANI..NOTO",
    "e0316059": "CS2103-T16-4 QU M..NGSI"
  }
}
